mylabs_mcp/__init__.py
mylabs_mcp/projectall_experts/__init__.py
mylabs_mcp_projectall_experts-0.2.0.dist-info/METADATA
mylabs_mcp_projectall_experts-0.2.0.dist-info/WHEEL
mylabs_mcp_projectall_experts-0.2.0.dist-info/entry_points.txt
mylabs_mcp_projectall_experts-0.2.0.dist-info/RECORD
