Metadata-Version: 2.4
Name: mylabs-mcp.projectall-experts
Version: 0.2.0
Summary: All Model Context Protocol (MCP) servers
Project-URL: Homepage, https://github.com/scottschreckengaust/mcpmonorepo
Project-URL: Repository, https://github.com/scottschreckengaust/mcpmonorepo.git
Author-email: Scott Schreckengaust <scottschreckengaust@users.noreply.github.com>
Requires-Python: >=3.13
Requires-Dist: mcp[cli]>=1.3.0
Requires-Dist: mylabs-mcp-projectfour-expert>=0.1.0
Requires-Dist: mylabs-mcp-projectsix-expert>=0.1.0
Requires-Dist: mylabs-mcp-projectten-expert>=0.1.0
Requires-Dist: pydantic>=2.10.6
